{
  "Views\\ShoppingListPage.xaml": {
    "ShoppingList": [
      {
        "Name": "Drinks",
        "Quantity": 2,
        "ScannedQuantity": 1,
        "QuantityLeft": 1
      },
      {
        "Name": "Cheese",
        "Quantity": 1,
        "ScannedQuantity": 0,
        "QuantityLeft": 1
      }
    ]
  },
  "Views\\ScannedListPage.xaml": {
    "SumText": "Sum: 250 CHF",
    "ScannedList": [
      {
        "Name": "Red bull adsfasdfasdfasdfasdfasdf",
        "Image": "red_bull.png",
        "Quantity": 1,
        "TotalPrice": 3
      },
      {
        "Name": "Red bull",
        "Image": "red_bull.png",
        "Quantity": 1,
        "TotalPrice": 3
      },
      {
        "Name": "Red bull",
        "Image": "red_bull.png",
        "Quantity": 1,
        "TotalPrice": 3
      }
    ]
  },
  "Views\\PaymentPage.xaml": {
    "PaymentText": "You have checked out the sum of {sum} CHF. Have a nice day!"
  }

}